README.rst
setup.cfg
setup.py
collective/__init__.py
collective.timelines.egg-info/PKG-INFO
collective.timelines.egg-info/SOURCES.txt
collective.timelines.egg-info/dependency_links.txt
collective.timelines.egg-info/entry_points.txt
collective.timelines.egg-info/namespace_packages.txt
collective.timelines.egg-info/not-zip-safe
collective.timelines.egg-info/paster_plugins.txt
collective.timelines.egg-info/requires.txt
collective.timelines.egg-info/top_level.txt
collective/timelines/__init__.py
collective/timelines/at_content.py
collective/timelines/config.py
collective/timelines/dexterity_content.py
collective/timelines/indexer.py
collective/timelines/interfaces.py
collective/timelines/map_support.py
collective/timelines/migration.py
collective/timelines/setuphandlers.py
collective/timelines/tests.py
collective/timelines/browser/__init__.py
collective/timelines/browser/configuration.py
collective/timelines/browser/view.py