Metadata-Version: 1.1
Name: collective.timelines
Version: 2.0
Summary: Timeline views for collections and folders (using verite TimelineJS).
Home-page: http://svn.plone.org/svn/collective/
Author: Alec Mitchell
Author-email: alecpm@gmail.com
License: GPL
Platform: UNKNOWN
Classifier: Framework :: Plone
Classifier: Programming Language :: Python
